lmdx_flow/__init__.py
lmdx_flow/pipeline.py
lmdx_flow/utils.py
lmdx_flow-0.1.2.dist-info/METADATA
lmdx_flow-0.1.2.dist-info/WHEEL
lmdx_flow-0.1.2.dist-info/RECORD
