Metadata-Version: 2.1
Name: lmdx-flow
Version: 0.1.2
Summary: Python toolkit for document information extraction using LMDX
Home-page: https://github.com/JazBern/LMDX-flow
Author: JazBern
Author-email: jasmine0696@gmail.com
Requires-Python: >=3.9,<3.13
Classifier: Programming Language :: Python :: 3
Classifier: Programming Language :: Python :: 3.9
Classifier: Programming Language :: Python :: 3.10
Classifier: Programming Language :: Python :: 3.11
Requires-Dist: pandas (>=2.1.1,<3.0.0)
Requires-Dist: pdf2image (>=1.16.3,<2.0.0)
Requires-Dist: poppler-utils (>=0.1.0,<0.2.0)
Requires-Dist: pytesseract (>=0.3.10,<0.4.0)
Requires-Dist: transformers (>=4.34.0,<5.0.0)
Project-URL: Repository, https://github.com/JazBern/LMDX-flow
